da_vinci/__init__.py
da_vinci/compat.py
da_vinci/formats.py
da_vinci/images.py
da_vinci/utils.py
da_vinci-0.5.0.dist-info/METADATA
da_vinci-0.5.0.dist-info/WHEEL
da_vinci-0.5.0.dist-info/top_level.txt
da_vinci-0.5.0.dist-info/RECORD
